aiogram_webhook/__init__.py
aiogram_webhook/adapters/__init__.py
aiogram_webhook/adapters/aiohttp.py
aiogram_webhook/adapters/base.py
aiogram_webhook/adapters/fastapi.py
aiogram_webhook/engines/__init__.py
aiogram_webhook/engines/base.py
aiogram_webhook/engines/simple.py
aiogram_webhook/engines/token.py
aiogram_webhook/routing/__init__.py
aiogram_webhook/routing/base.py
aiogram_webhook/routing/path.py
aiogram_webhook/routing/query.py
aiogram_webhook/security/__init__.py
aiogram_webhook/security/secret_token.py
aiogram_webhook/security/security.py
aiogram_webhook/security/checks/__init__.py
aiogram_webhook/security/checks/check.py
aiogram_webhook/security/checks/ip.py
aiogram_webhook-0.2.0.dist-info/METADATA
aiogram_webhook-0.2.0.dist-info/WHEEL
aiogram_webhook-0.2.0.dist-info/licenses/LICENSE
aiogram_webhook-0.2.0.dist-info/RECORD
