Metadata-Version: 2.4
Name: aiogram-webhook
Version: 0.2.0
Summary: A python library for integrating webhook support with multiple web frameworks in aiogram. Organizes bot operation via webhooks for both single and multi-bot setups.
Project-URL: Homepage, https://github.com/m-xim/aiogram-webhook
Project-URL: Repository, https://github.com/m-xim/aiogram-webhook
Project-URL: Issues, https://github.com/m-xim/aiogram-webhook/issues
Project-URL: Documentation, https://github.com/m-xim/aiogram-webhook#readme
Author-email: m-xim <i@m-xim.ru>
License: MIT
License-File: LICENSE
Keywords: aiogram,aiohttp,fastapi,multibot,telegram,webhook
Classifier: Operating System :: OS Independent
Classifier: Programming Language :: Python :: 3
Classifier: Programming Language :: Python :: 3.10
Classifier: Programming Language :: Python :: 3.11
Classifier: Programming Language :: Python :: 3.12
Classifier: Programming Language :: Python :: 3.13
Classifier: Topic :: Software Development :: Libraries
Requires-Python: >=3.10
Requires-Dist: aiogram>=3.14.0
Requires-Dist: yarl>=1.17.0
Provides-Extra: aiohttp
Requires-Dist: aiohttp>=3.9.0; extra == 'aiohttp'
Provides-Extra: dev
Requires-Dist: httpx; extra == 'dev'
Requires-Dist: pytest; extra == 'dev'
Requires-Dist: pytest-asyncio; extra == 'dev'
Requires-Dist: ruff; extra == 'dev'
Requires-Dist: ty; extra == 'dev'
Provides-Extra: fastapi
Requires-Dist: fastapi>=0.128.0; extra == 'fastapi'
